README.rst
docutils_graphviz.py
setup.py
python_docutils_graphviz.egg-info/PKG-INFO
python_docutils_graphviz.egg-info/SOURCES.txt
python_docutils_graphviz.egg-info/dependency_links.txt
python_docutils_graphviz.egg-info/requires.txt
python_docutils_graphviz.egg-info/top_level.txt