Metadata-Version: 1.0
Name: python-docutils-graphviz
Version: 1.0.1
Summary: Graphviz extension for docutils
Home-page: https://github.com/liuyug/python-docutils-graphviz.git
Author: Yugang LIU
Author-email: liuyug@gmail.com
License: MIT
Platform: UNKNOWN
